{"openapi":"3.0.1","info":{"title":"Login API","version":"2.0"},"servers":[{"url":"http://218.39.10.56:31250","description":"Generated server url"}],"security":[{"token":[]}],"tags":[{"name":"auth","description":"로그인 API"}],"paths":{"/auth/social":{"get":{"tags":["auth"],"summary":"소셜 유저 존재 확인","description":"소셜 유저가 DB에 있는지 확인하는 api","operationId":"isExistSocialUser","parameters":[{"name":"socialId","in":"query","required":true,"schema":{"type":"string"}},{"name":"platform","in":"query","required":true,"schema":{"type":"string"}}],"responses":{"500":{"description":"Internal Server Error","content":{"application/json":{"schema":{"$ref":"#/components/schemas/ErrorResponse"}}}},"401":{"description":"Unauthorized","content":{"application/json":{"schema":{"$ref":"#/components/schemas/ErrorResponse"}}}},"404":{"description":"Not Found","content":{"application/json":{"schema":{"$ref":"#/components/schemas/ErrorResponse"}}}},"400":{"description":"Bad Request","content":{"application/json":{"schema":{"$ref":"#/components/schemas/ErrorResponse"}}}},"200":{"description":"OK","content":{"application/json":{"schema":{"type":"object"}}}}}},"post":{"tags":["auth"],"summary":"소셜 로그인 - JSON Web Token 반환","description":"네이버, 구글, 카카오등 소셜 유저의 인증토큰생성하여 반환한다","operationId":"socialAuth","requestBody":{"content":{"application/json":{"schema":{"$ref":"#/components/schemas/GetSocialTokenReq"}}},"required":true},"responses":{"500":{"description":"Internal Server Error","content":{"application/json":{"schema":{"$ref":"#/components/schemas/ErrorResponse"}}}},"401":{"description":"Unauthorized","content":{"application/json":{"schema":{"$ref":"#/components/schemas/ErrorResponse"}}}},"404":{"description":"Not Found","content":{"application/json":{"schema":{"$ref":"#/components/schemas/ErrorResponse"}}}},"400":{"description":"Bad Request","content":{"application/json":{"schema":{"$ref":"#/components/schemas/ErrorResponse"}}}},"200":{"description":"OK","content":{"application/json":{"schema":{"$ref":"#/components/schemas/GetTokenRes"}}}}}}},"/auth/social-decode":{"post":{"tags":["auth"],"operationId":"decode","requestBody":{"content":{"application/json":{"schema":{"$ref":"#/components/schemas/EncodedDto"}}},"required":true},"responses":{"500":{"description":"Internal Server Error","content":{"application/json":{"schema":{"$ref":"#/components/schemas/ErrorResponse"}}}},"401":{"description":"Unauthorized","content":{"application/json":{"schema":{"$ref":"#/components/schemas/ErrorResponse"}}}},"404":{"description":"Not Found","content":{"application/json":{"schema":{"$ref":"#/components/schemas/ErrorResponse"}}}},"400":{"description":"Bad Request","content":{"application/json":{"schema":{"$ref":"#/components/schemas/ErrorResponse"}}}},"200":{"description":"OK","content":{"application/json":{"schema":{"type":"object"}}}}}}},"/auth/password":{"post":{"tags":["auth"],"summary":"비밀번호 수정","description":"로그인한 상태에서 비밀번호를 수정하면 임시비밀번호 상태를 업데이트하고 새로운 비밀번호로 업데이트한다","operationId":"changePassword","requestBody":{"content":{"application/json":{"schema":{"$ref":"#/components/schemas/ChangePwReq"}}},"required":true},"responses":{"500":{"description":"Internal Server Error","content":{"application/json":{"schema":{"$ref":"#/components/schemas/ErrorResponse"}}}},"401":{"description":"Unauthorized","content":{"application/json":{"schema":{"$ref":"#/components/schemas/ErrorResponse"}}}},"404":{"description":"Not Found","content":{"application/json":{"schema":{"$ref":"#/components/schemas/ErrorResponse"}}}},"400":{"description":"Bad Request","content":{"application/json":{"schema":{"$ref":"#/components/schemas/ErrorResponse"}}}},"200":{"description":"OK"}},"security":[{"token":[]}]}},"/auth/password/email":{"post":{"tags":["auth"],"summary":"비밀번호 찾기 기능 - 이메일","description":"사용자가 아이디를 입력하면 조회하여 유효한 아이디라면 임시비밀번호 생성 후 메일로 전송한다","operationId":"pwReissueEmail","parameters":[{"name":"projectCd","in":"query","description":"프로젝트 코드","required":true,"schema":{"type":"string","example":"O2MEET"}},{"name":"siteId","in":"query","description":"사이트 아이디","required":false,"schema":{"type":"string","example":99001}}],"requestBody":{"content":{"application/json":{"schema":{"$ref":"#/components/schemas/FindPwReq"}}},"required":true},"responses":{"500":{"description":"Internal Server Error","content":{"application/json":{"schema":{"$ref":"#/components/schemas/ErrorResponse"}}}},"401":{"description":"Unauthorized","content":{"application/json":{"schema":{"$ref":"#/components/schemas/ErrorResponse"}}}},"404":{"description":"Not Found","content":{"application/json":{"schema":{"$ref":"#/components/schemas/ErrorResponse"}}}},"400":{"description":"Bad Request","content":{"application/json":{"schema":{"$ref":"#/components/schemas/ErrorResponse"}}}},"200":{"description":"OK","content":{"application/json":{"schema":{"type":"string"}}}}}}},"/auth/local":{"post":{"tags":["auth"],"summary":"통합 로그인(토큰생성) - JSON Web Token 반환","description":"인증후 토큰을 생성하여 반환한다","operationId":"localAuth","requestBody":{"content":{"application/json":{"schema":{"$ref":"#/components/schemas/GetTokenReq"}}},"required":true},"responses":{"500":{"description":"Internal Server Error","content":{"application/json":{"schema":{"$ref":"#/components/schemas/ErrorResponse"}}}},"401":{"description":"Unauthorized","content":{"application/json":{"schema":{"$ref":"#/components/schemas/ErrorResponse"}}}},"404":{"description":"Not Found","content":{"application/json":{"schema":{"$ref":"#/components/schemas/ErrorResponse"}}}},"400":{"description":"Bad Request","content":{"application/json":{"schema":{"$ref":"#/components/schemas/ErrorResponse"}}}},"200":{"description":"OK","content":{"application/json":{"schema":{"$ref":"#/components/schemas/GetTokenRes"}}}}}}},"/auth/id-list":{"post":{"tags":["auth"],"summary":"아이디 찾기 기능","description":"사용자가 이름, 번호를 입력하면 아이디 목록을 반환한다","operationId":"findIdList","requestBody":{"content":{"application/json":{"schema":{"$ref":"#/components/schemas/FindIdReq"}}},"required":true},"responses":{"500":{"description":"Internal Server Error","content":{"application/json":{"schema":{"$ref":"#/components/schemas/ErrorResponse"}}}},"401":{"description":"Unauthorized","content":{"application/json":{"schema":{"$ref":"#/components/schemas/ErrorResponse"}}}},"404":{"description":"Not Found","content":{"application/json":{"schema":{"$ref":"#/components/schemas/ErrorResponse"}}}},"400":{"description":"Bad Request","content":{"application/json":{"schema":{"$ref":"#/components/schemas/ErrorResponse"}}}},"200":{"description":"OK","content":{"application/json":{"schema":{"type":"array","items":{"type":"object","additionalProperties":{"type":"object"}}}}}}}}},"/auth/email":{"post":{"tags":["auth"],"summary":"가입 인증 - 이메일","description":"랜덤키가 담긴 가입 인증을 확인하는 이메일을 전송한다 - 유효 시간 3분","operationId":"verifySignUpEmail","parameters":[{"name":"projectCd","in":"query","description":"프로젝트 코드","required":true,"schema":{"type":"string","example":"O2MEET"}},{"name":"siteId","in":"query","description":"사이트 아이디","required":false,"schema":{"type":"string","example":99001}}],"requestBody":{"content":{"application/json":{"schema":{"$ref":"#/components/schemas/MailAuthReq"}}},"required":true},"responses":{"500":{"description":"Internal Server Error","content":{"application/json":{"schema":{"$ref":"#/components/schemas/ErrorResponse"}}}},"401":{"description":"Unauthorized","content":{"application/json":{"schema":{"$ref":"#/components/schemas/ErrorResponse"}}}},"404":{"description":"Not Found","content":{"application/json":{"schema":{"$ref":"#/components/schemas/ErrorResponse"}}}},"400":{"description":"Bad Request","content":{"application/json":{"schema":{"$ref":"#/components/schemas/ErrorResponse"}}}},"200":{"description":"OK"}}}},"/auth/admin/password":{"post":{"tags":["auth"],"summary":"비밀번호 수정","description":"로그인한 상태에서 비밀번호를 수정하면 임시비밀번호 상태를 업데이트하고 새로운 비밀번호로 업데이트한다","operationId":"changePasswordByAdmin","requestBody":{"content":{"application/json":{"schema":{"$ref":"#/components/schemas/ChangePwAdminReq"}}},"required":true},"responses":{"500":{"description":"Internal Server Error","content":{"application/json":{"schema":{"$ref":"#/components/schemas/ErrorResponse"}}}},"401":{"description":"Unauthorized","content":{"application/json":{"schema":{"$ref":"#/components/schemas/ErrorResponse"}}}},"404":{"description":"Not Found","content":{"application/json":{"schema":{"$ref":"#/components/schemas/ErrorResponse"}}}},"400":{"description":"Bad Request","content":{"application/json":{"schema":{"$ref":"#/components/schemas/ErrorResponse"}}}},"200":{"description":"OK"}},"security":[{"token":[]}]}},"/auth/{verifyKey}":{"get":{"tags":["auth"],"summary":"인증","description":"발급받은 번호로 인증한다","operationId":"authenticateNumber","parameters":[{"name":"verifyKey","in":"path","required":true,"schema":{"type":"string"}},{"name":"userId","in":"query","required":false,"schema":{"type":"string"}},{"name":"projectCd","in":"query","required":false,"schema":{"type":"string"}},{"name":"siteId","in":"query","required":false,"schema":{"type":"integer","format":"int32"}}],"responses":{"500":{"description":"Internal Server Error","content":{"application/json":{"schema":{"$ref":"#/components/schemas/ErrorResponse"}}}},"401":{"description":"Unauthorized","content":{"application/json":{"schema":{"$ref":"#/components/schemas/ErrorResponse"}}}},"404":{"description":"Not Found","content":{"application/json":{"schema":{"$ref":"#/components/schemas/ErrorResponse"}}}},"400":{"description":"Bad Request","content":{"application/json":{"schema":{"$ref":"#/components/schemas/ErrorResponse"}}}},"200":{"description":"OK","content":{"application/json":{"schema":{"type":"object"}}}}}}},"/auth/me":{"get":{"tags":["auth"],"summary":"내 정보 api","description":"내 정보 api","operationId":"testMe","responses":{"500":{"description":"Internal Server Error","content":{"application/json":{"schema":{"$ref":"#/components/schemas/ErrorResponse"}}}},"401":{"description":"Unauthorized","content":{"application/json":{"schema":{"$ref":"#/components/schemas/ErrorResponse"}}}},"404":{"description":"Not Found","content":{"application/json":{"schema":{"$ref":"#/components/schemas/ErrorResponse"}}}},"400":{"description":"Bad Request","content":{"application/json":{"schema":{"$ref":"#/components/schemas/ErrorResponse"}}}},"200":{"description":"OK","content":{"application/json":{"schema":{"$ref":"#/components/schemas/AuthToken"}}}}},"security":[{"token":[]}]}}},"components":{"schemas":{"ErrorResponse":{"type":"object","properties":{"httpStatus":{"type":"integer","format":"int32"},"errorMessage":{"type":"string"},"detailMessage":{"type":"string"},"errors":{"type":"array","items":{"$ref":"#/components/schemas/FieldError"}}}},"FieldError":{"type":"object","properties":{"field":{"type":"string"},"value":{"type":"string"},"reason":{"type":"string"}}},"GetSocialTokenReq":{"required":["platform","socialId"],"type":"object","properties":{"projectCd":{"type":"string","description":"프로젝트 코드","example":"common"},"siteId":{"type":"integer","description":"사이트 아이디","format":"int32","example":9999},"socialId":{"type":"string","description":"Social Id","example":"2114156716"},"platform":{"type":"string","description":"Platform","example":"kakao"}}},"GetTokenRes":{"type":"object","properties":{"token":{"type":"string","description":"Json Web token 값"}}},"EncodedDto":{"type":"object","properties":{"token":{"type":"string"}}},"ChangePwReq":{"required":["newPassWd","oldPassWd"],"type":"object","properties":{"oldPassWd":{"type":"string","description":"예전 비밀번호 혹은 발급받은 임시 비밀번호를 입력","example":"past_password"},"newPassWd":{"type":"string","description":"'숫자', '문자', '특수문자' 무조건 1개 이상, 비밀번호 '최소 8자에서 최대 16자'까지 허용","example":"1q2w3e4r2022!@"}}},"FindPwReq":{"required":["userId"],"type":"object","properties":{"userId":{"type":"string","description":"이메일 주소","example":"o2meet@o2meet.io"},"firstNumber":{"type":"string","description":"국가 번호 입력","example":"82"},"lastNumber":{"type":"string","description":"핸드폰 번호(-)빼고 입력","example":"01022223333"},"mailInfo":{"$ref":"#/components/schemas/MailInfo"}}},"MailInfo":{"required":["emailTitle","senderNm","senderType","templateType"],"type":"object","properties":{"templateType":{"type":"string","description":"가입인증 탬플릿코드 (EMC901)<br/>, 비밀번호 찾기코드(EMC902)","example":"EMC901"},"senderType":{"type":"string","description":"공통 발신코드","example":"EMC999"},"langCd":{"maxLength":2,"minLength":2,"type":"string","description":"언어코드(KR,EN)","example":"KR"},"emailTitle":{"type":"string","description":"이메일 제목 입력","example":"[O2MEET] 회원가입 인증"},"senderNm":{"type":"string","description":"행사명 + 사무국","example":"O2MEET 사무국"},"event":{"type":"string","description":"행사 이름"},"subject1":{"type":"string","description":"site > site_nm","example":"행사명"},"subject2":{"type":"string","description":"site > site_summary","example":"행사 부연설명"},"url":{"type":"string","description":"site > site_domain","example":"https://o2meet.io"},"logo":{"type":"string","description":"site > site_logo","example":"로고 주소"}}},"GetTokenReq":{"required":["userId","userPasswd"],"type":"object","properties":{"projectCd":{"type":"string","description":"프로젝트 코드","example":"common"},"siteId":{"type":"integer","description":"사이트 아이디","format":"int32","example":9999},"userId":{"type":"string","description":"User ID","example":"ezpmp_user"},"userPasswd":{"type":"string","description":"User Password","example":"ezpmp3475"},"rememberMe":{"pattern":"^(Y|N)$","type":"string","description":"Remember Condition","example":"N"},"resMsgPw":{"type":"string","description":"언어별 응답 메세지","example":"비밀번호가 맞지 않습니다."},"resMsgLogin":{"type":"string","description":"언어별 응답 메세지","example":"로그인 실패 횟수가 5번을 초과했습니다."}}},"FindIdReq":{"required":["firstNumber","lastNumber"],"type":"object","properties":{"firstNumber":{"type":"string","description":"국가 번호 입력","example":"82"},"lastNumber":{"type":"string","description":"핸드폰 번호(-)빼고 입력","example":"01022223333"}}},"MailAuthReq":{"required":["userId"],"type":"object","properties":{"userId":{"type":"string","description":"사용자가 입력한 이메일 주소","example":"o2meet@o2meet.io"},"mailInfo":{"$ref":"#/components/schemas/MailInfo"}}},"ChangePwAdminReq":{"required":["password"],"type":"object","properties":{"userNo":{"type":"integer","format":"int32"},"password":{"type":"string"}}},"AuthToken":{"type":"object","properties":{"tokenType":{"type":"string"},"userNo":{"type":"integer","format":"int32"},"userId":{"type":"string"},"sites":{"type":"array","items":{"type":"object","additionalProperties":{"type":"object"}}},"authorities":{"type":"array","items":{"$ref":"#/components/schemas/GrantedAuthority"}}}},"GrantedAuthority":{"type":"object","properties":{"authority":{"type":"string"}}}},"securitySchemes":{"token":{"type":"apiKey","name":"Authorization","in":"header"}}}}